postfinance/__init__.py
postfinance/agent.py
postfinance/annotate.py
postfinance/settings.py
postfinance/storage.py
postfinance/tools/__init__.py
postfinance/tools/graph_qa_tool.py
postfinance/tools/summarization_tool.py
postfinance/tools/translation_tool.py
postfinance/tools/vector_search_tool.py
postfinance/translate.py
postfinancex-0.0.9.dist-info/LICENSE
postfinancex-0.0.9.dist-info/METADATA
postfinancex-0.0.9.dist-info/WHEEL
postfinancex-0.0.9.dist-info/RECORD
