Metadata-Version: 2.1
Name: postfinancex
Version: 0.0.9
Summary: PostFinanceX Virtual Assistant powered by IBM watsonx.ai ✨ PostFinance X IBM watsonx.ai
Home-page: https://pypi.org/project/postfinancex
License: BSD-3-Clause
Author: Yi ZHANG
Author-email: yizhang.dev@gmail.com
Requires-Python: >=3.10,<4.0
Classifier: License :: OSI Approved :: BSD License
Classifier: Programming Language :: Python :: 3
Classifier: Programming Language :: Python :: 3.10
Classifier: Programming Language :: Python :: 3.11
Classifier: Programming Language :: Python :: 3.12
Requires-Dist: dnspython (>=2.6.1,<3.0.0)
Requires-Dist: ibm_watsonx_ai (>=1.0.4,<2.0.0)
Requires-Dist: langchain (>=0.2.0,<0.3.0)
Requires-Dist: langchain-community (>=0.2.1,<0.3.0)
Requires-Dist: langchain-ibm (>=0.1.7,<0.2.0)
Requires-Dist: llama-index (>=0.10.38,<0.11.0)
Requires-Dist: llama-index-embeddings-jinaai (>=0.1.5,<0.2.0)
Requires-Dist: llama-index-llms-watsonx (>=0.1.7,<0.2.0)
Requires-Dist: neo4j (>=5.20.0,<6.0.0)
Requires-Dist: pymongo (>=4.7.2,<5.0.0)
Project-URL: Repository, https://github.com/imyizhang/postfinancex
